{
  "schemaVersion": 1,
  "environment": {
    "kind": "studio",
    "intensity": 1.0,
    "rotationRadians": 0.0,
    "showSkybox": false,
    "skyboxBlur": 0.0
  },
  "lighting": {
    "kind": "studio",
    "exposure": 1.0,
    "ambientOcclusion": false,
    "environmentIntensity": 1.0,
    "keyLightIntensity": 3.0,
    "keyLightColor": [1.0, 1.0, 1.0],
    "keyLightDirection": [-0.45, -0.85, -0.35],
    "keyLightCastsShadow": false
  },
  "camera": {
    "fit": "assetBounds",
    "views": ["front", "left", "right", "back"]
  }
}
